{
  "parameters": [
    {
      "name": "data-tchmi-baobject",
      "displayName": "BaObject",
      "visible": true,
      "type": "tchmi:framework#/definitions/Symbol",
      "category": "BA",
      "description": "The BaObject of the AHU",
      "requiredOnCompile": false,
      "readOnly": false,
      "bindable": true,
      "heritable": true,
      "propertyName": "BaObject",
      "propertySetterName": "setBaObject",
      "propertyGetterName": "getBaObject",
      "refTo": ""
    }
  ],
  "virtualRights": [],
  "$schema": "./../../Packages/Beckhoff.TwinCAT.HMI.Framework.12.758.8/runtimes/native1.12-tchmi/Schema/UserControlConfig.Schema.json",
  "description": ""
}